telefly/__init__.py
telefly-0.1.3.dist-info/METADATA
telefly-0.1.3.dist-info/WHEEL
telefly-0.1.3.dist-info/top_level.txt
telefly-0.1.3.dist-info/RECORD
