Metadata-Version: 2.1
Name: telefly
Version: 0.1.3
Summary: Create Telegram bots in Python.
Home-page: https://github.com/ztpnk/telefly
Author: Zeitpunk
Author-email: ztpnk@mailbox.org
License: UNKNOWN
Platform: UNKNOWN
Classifier: Programming Language :: Python :: 3
